grimoire_context/__init__.py
grimoire_context/context.py
grimoire_context/exceptions.py
grimoire_context/logging.py
grimoire_context/merge.py
grimoire_context/path_resolver.py
grimoire_context/protocols.py
grimoire_context-0.3.1.dist-info/licenses/LICENSE
grimoire_context-0.3.1.dist-info/METADATA
grimoire_context-0.3.1.dist-info/WHEEL
grimoire_context-0.3.1.dist-info/top_level.txt
grimoire_context-0.3.1.dist-info/RECORD
