Metadata-Version: 2.4
Name: grimoire-context
Version: 0.3.1
Summary: Immutable, hierarchical context management for Grimoire
Author-email: The Wyrd one <wyrdbound@proton.me>
License: MIT
Project-URL: Homepage, https://github.com/wyrdbound/grimoire-context
Project-URL: Repository, https://github.com/wyrdbound/grimoire-context
Project-URL: Issues, https://github.com/wyrdbound/grimoire-context/issues
Classifier: Development Status :: 4 - Beta
Classifier: Intended Audience :: Developers
Classifier: License :: OSI Approved :: MIT License
Classifier: Programming Language :: Python :: 3
Classifier: Programming Language :: Python :: 3.8
Classifier: Programming Language :: Python :: 3.9
Classifier: Programming Language :: Python :: 3.10
Classifier: Programming Language :: Python :: 3.11
Classifier: Programming Language :: Python :: 3.12
Requires-Python: >=3.8
License-File: LICENSE
Requires-Dist: pyrsistent>=0.19.0
Requires-Dist: grimoire-logging>=0.1.0
Provides-Extra: dev
Requires-Dist: pytest>=7.0; extra == "dev"
Requires-Dist: pytest-cov>=4.0; extra == "dev"
Requires-Dist: mypy>=1.0; extra == "dev"
Requires-Dist: ruff>=0.0.290; extra == "dev"
Dynamic: license-file
